goputn/__init__.py
goputn-0.3.1.dist-info/METADATA
goputn-0.3.1.dist-info/WHEEL
goputn-0.3.1.dist-info/entry_points.txt
goputn-0.3.1.dist-info/top_level.txt
goputn-0.3.1.dist-info/RECORD
