Metadata-Version: 2.1
Name: goputn
Version: 0.3.1
Summary: Branded runtime with gopuTN, goputn, gotn commands
Home-page: https://github.com/gopu-inc/gopuTNS
Author: Ceose
Classifier: Programming Language :: Python :: 3
Classifier: Operating System :: OS Independent
